inmanta_plugins/openstack/__init__.py
inmanta_plugins/openstack/setup.cfg
inmanta_plugins/openstack/model/_init.cf
inmanta_module_openstack-4.0.8.dist-info/METADATA
inmanta_module_openstack-4.0.8.dist-info/WHEEL
inmanta_module_openstack-4.0.8.dist-info/top_level.txt
inmanta_module_openstack-4.0.8.dist-info/RECORD
