Metadata-Version: 2.1
Name: inmanta-module-openstack
Version: 4.0.8
License: Apache 2.0
Requires-Dist: inmanta-module-ssh
Requires-Dist: inmanta-module-std
Requires-Dist: python-dateutil<3,>=2.8
Requires-Dist: python-keystoneclient<6,>=5.1
Requires-Dist: python-novaclient<19,>=18.3
Requires-Dist: python-neutronclient<12,>=9.0
Requires-Dist: python-glanceclient<4.8
Requires-Dist: netifaces<1,>=0.11
